{
  "schema_version": "patient_case_v1",
  "demographics": {
    "age": 34,
    "sex": "female"
  },
  "chief_complaint": "Sore throat and fever for three days.",
  "symptoms": [
    {
      "description": "Painful swallowing",
      "onset": "3 days ago",
      "severity": "moderate",
      "duration": "3 days"
    },
    {
      "description": "Fever",
      "onset": "2 days ago",
      "severity": "low",
      "duration": "intermittent"
    }
  ],
  "history": "No chronic illnesses. Non-smoker.",
  "medications": [],
  "allergies": ["Penicillin (rash)"],
  "vitals": {
    "temperature_c": 38.1,
    "heart_rate_bpm": 92
  },
  "labs": null
}
